conditional_field
tests
